arxiv/__init__.py
arxiv/arxiv.py
arxiv-2.3.2.dist-info/licenses/LICENSE.txt
arxiv-2.3.2.dist-info/METADATA
arxiv-2.3.2.dist-info/WHEEL
arxiv-2.3.2.dist-info/top_level.txt
arxiv-2.3.2.dist-info/RECORD
