Metadata-Version: 2.4
Name: arxiv
Version: 2.3.2
Summary: Python wrapper for the arXiv API: https://arxiv.org/help/api/
Home-page: https://github.com/lukasschwab/arxiv.py
Author: Lukas Schwab
Author-email: lukas.schwab@gmail.com
License: MIT
Keywords: arxiv api wrapper academic journals papers
Classifier: Programming Language :: Python
Classifier: Programming Language :: Python :: 3.9
Classifier: Programming Language :: Python :: 3.10
Classifier: Programming Language :: Python :: 3.11
Classifier: Programming Language :: Python :: 3.12
Classifier: Programming Language :: Python :: 3.13
Classifier: License :: OSI Approved :: MIT License
Classifier: Operating System :: OS Independent
Requires-Python: >=3.7
License-File: LICENSE.txt
Requires-Dist: feedparser~=6.0.10
Requires-Dist: requests~=2.32.0
Dynamic: author
Dynamic: author-email
Dynamic: classifier
Dynamic: description
Dynamic: description-content-type
Dynamic: home-page
Dynamic: keywords
Dynamic: license
Dynamic: license-file
Dynamic: requires-dist
Dynamic: requires-python
Dynamic: summary
